tickermood/__init__.py
tickermood/agent.py
tickermood/articles.py
tickermood/database/__init__.py
tickermood/database/alembic/README
tickermood/database/alembic/alembic.ini
tickermood/database/alembic/env.py
tickermood/database/alembic/script.py.mako
tickermood/database/alembic/versions/6e324523861c_.py
tickermood/database/alembic/versions/e5ba9b601ea5_.py
tickermood/database/alembic/versions/ea815a161929_.py
tickermood/database/crud.py
tickermood/database/schemas.py
tickermood/database/scripts/create_revision.py
tickermood/database/scripts/upgrade.py
tickermood/database/settings.py
tickermood/exceptions.py
tickermood/main.py
tickermood/source.py
tickermood/subject.py
tickermood/types.py
tickermood-0.29.0.dist-info/METADATA
tickermood-0.29.0.dist-info/WHEEL
tickermood-0.29.0.dist-info/entry_points.txt
tickermood-0.29.0.dist-info/RECORD
