Metadata-Version: 2.3
Name: tickermood
Version: 0.29.0
Summary: 
Author: aan
Author-email: andoludovic.andriamamonjy@gmail.com
Requires-Python: >=3.10,<4.0
Classifier: Programming Language :: Python :: 3
Classifier: Programming Language :: Python :: 3.10
Classifier: Programming Language :: Python :: 3.11
Classifier: Programming Language :: Python :: 3.12
Classifier: Programming Language :: Python :: 3.13
Requires-Dist: alembic (>=1.14.0,<2.0.0)
Requires-Dist: googlesearch-python (>=1.3.0,<2.0.0)
Requires-Dist: langchain (>=0.3.25,<0.4.0)
Requires-Dist: langchain-ollama (>=0.3.3,<0.4.0)
Requires-Dist: langchain-openai (>=0.3.18,<0.4.0)
Requires-Dist: langgraph (>=0.4.7,<0.5.0)
Requires-Dist: lxml (>=5.4.0,<6.0.0)
Requires-Dist: lxml-html-clean (>=0.4.2,<0.5.0)
Requires-Dist: newspaper3k (>=0.2.8,<0.3.0)
Requires-Dist: ollama (>=0.4.8,<0.5.0)
Requires-Dist: openai (>=1.79.0,<2.0.0)
Requires-Dist: pandas (>=2.1.4,<3.0.0)
Requires-Dist: pydantic (>=2.5.3,<3.0.0)
Requires-Dist: pydotenv (>=0.0.7,<0.0.8)
Requires-Dist: python-dotenv (>=1.0.1,<2.0.0)
Requires-Dist: selenium (>=4.32.0,<5.0.0)
Requires-Dist: sqlmodel (>=0.0.22,<0.0.23)
Requires-Dist: typer (>=0.13.1,<0.14.0)
Requires-Dist: undetected-chromedriver (>=3.5.5,<4.0.0)
Requires-Dist: webdriver-manager (>=4.0.2,<5.0.0)
Requires-Dist: yfinance (>=0.2.63,<0.3.0)
